<?xml version="1.0" encoding="utf-8"?>
<InstanceSettings xmlns:xsi="http://www.w3.org/2001/XMLSchema-instance" xsi:noNamespaceSchemaLocation="http://files.d03n3r.de/TS3bot_Settings_v1.xsd">

    <!-- true/false | Enables/Disables the whole Bot. -->
    <Enabled>false</Enabled>

    <!-- Some additional Bot settings. -->
    <Global>
        <!-- The nickname of the bot. Will be visible, when the bot messages, moves or kicks someone. -->
        <BotNickname>Bot</BotNickname>
        
        <!-- Sets the Culture Information for the correct number and datetime formatting. -->
        <Globalization>en-US</Globalization>
    </Global>

    <!-- The TeamSpeak settings, which will be used to connect and interact with the TeamSpeak Server. -->
    <TeamSpeak>
        <!-- Specify the IP or Host of your TeamSpeak Server. -->
	<Host>127.0.0.1</Host>
		
	<!-- Specify the Username of any ServerQuery-User. Be sure that this account has enough rights to do, what you configure below ;-) -->
        <Username></Username>
		
	<!-- Specify the Password for the Username above. -->
        <Password></Password>
		
	<!-- Specify the Server Instance ID, on which this Bot will be running. -->
        <Instance>1</Instance>
		
	<!-- Specify the Server Query Port, on which this Bot has to connect. -->
        <QueryPort>10011</QueryPort>
		
	<!-- Specify the ID of the Guest Group. -->
        <GuestGroups>
            <Group>8</Group>
        </GuestGroups>
    </TeamSpeak>

    <!-- Enabled: true/false    | Enables/Disables the Away-Channel. -->
    <!-- LogEnabled: true/false | Enables/Disables the Logging of this feature. -->
    <Away Enabled="true">
        <!-- The ID of the away channel, where someone will be moved, when he/she is away. -->
        <Channel>2</Channel>
		
        <!-- The ID of the away channel, where someone will be moved, when he/she mutes his/her headphones. -->
        <MuteHeadphoneChannel>3</MuteHeadphoneChannel>
		
        <!-- The ID of the away channel, where someone will be moved, when he/she mutes his/her microphone -->
        <MuteMicrophoneChannel>4</MuteMicrophoneChannel>
		
        <!-- Denied/Permitted-Tags can be placed here. For further details look at the example in the Vote feature.-->
    </Away>

    <!-- Enabled: true/false    | Enables/Disables the Bad-Nickname filter. -->
    <!-- LogEnabled: true/false | Enables/Disables the Logging of this feature. -->
    <BadNickname Enabled="true" LogEnabled="true">
        <!-- The List of Strings, which will be searched in nicknames. -->
        <!-- Be careful, cause the String can be anywhere in the nickname. So "ass" will also prevent nicknames like "Assassin". -->
        <Blacklist>
            <Entry>http:</Entry>
            <Entry>ftp:</Entry>
            <Entry>www.</Entry>
            <Entry>pussy</Entry>
            <Entry>fuck</Entry>
            <Entry>shit</Entry>
        </Blacklist>
        
        <!-- The Message that will be shown, when someone get kicked by this feature. -->
        <KickMessage>Thats a bad nickname!</KickMessage>
		
        <!-- Denied/Permitted-Tags can be placed here. For further details look at the example in the Vote feature.-->
    </BadNickname>

    <Control>
        <!-- The beginning of the Help-Message, when someone uses !help -->
        <HelpMessage>
            You can type following commands into the global chat to control me:
        </HelpMessage>

        <!-- Enabled: true/false    | Enables/Disables the !help-Command. -->
        <!-- LogEnabled: true/false | Enables/Disables the Logging of this feature. -->
        <Help Enabled="true">
            <!-- The Help-Message part, which will explain the !help-Command -->
            <HelpMessage>
                [B]!help[/B]
                Opens this help. Who would have thought it.
            </HelpMessage>
			
            <!-- Denied/Permitted-Tags can be placed here. For further details look at the example in the Vote feature.-->
        </Help>

        <!-- Enabled: true/false    | Enables/Disables the !seen-Command. -->
        <!-- LogEnabled: true/false | Enables/Disables the Logging of this feature. -->
        <Seen Enabled="true">
            <!-- The Help-Message part, which will explain the !seen-Command -->
            <HelpMessage>
                [B]!seen {Nickname|Database ID}[/B]
                Gives you information about when someone was last seen. It is enough to specify a part of the nickname. Alternatively, the database ID can be specified.
                Example: [I]!seen Stefan[/I]
            </HelpMessage>
			
            <!-- The text message, which will be shown, when someone uses the !seen-Command -->
            <TextMessage>
                About '[B][CLIENT_NICKNAME][/B]'(id:[CLIENT_ID]):
                Last logged in: [B][CLIENT_LASTLOGIN][/B]
                Last seen: [B][CLIENT_LASTSEEN][/B]
            </TextMessage>
			
            <!-- Denied/Permitted-Tags can be placed here. For further details look at the example in the Vote feature.-->
        </Seen>

        <!-- Enabled: true/false    | Enables/Disables the !files-Command. -->
        <!-- LogEnabled: true/false | Enables/Disables the Logging of this feature. -->
        <Files Enabled="true">
            <!-- The Help-Message part, which will explain the !files-Command -->
            <HelpMessage>
                [B]!files[/B]
                Gives you a list of all files in all rooms, grouped by virtual servers, if you are server admin :-)
            </HelpMessage>
			
            <!-- The message, which will be repeated for every server -->
            <MessagePerServer>Files on server '[B][SERVER_NAME][/B]' (Id: [SERVER_ID], Port: [SERVER_PORT]):</MessagePerServer>
			
            <!-- The message, which will be shown, when no files were found. -->
            <MessageNoFilesFound>No files were found.</MessageNoFilesFound>
			
            <!-- The message, which will be shown, when files were found. -->
            <MessageFilesFound>The following files were found:</MessageFilesFound>
			
            <!-- The message, which will be repeated for every file, which were found. -->
            <MessageFile>'[B][CHANNEL_NAME][/B]'(id:[CHANNEL_ID]) > '[B][FILE_NAME][/B]' (Created: [FILE_CREATED], Size: [FILE_SIZE])</MessageFile>
            
            <!-- Denied/Permitted-Tags can be placed here. For further details look at the example in the Vote feature.-->
            <Permitted>
                <Group>2</Group>
                <Group>6</Group>
            </Permitted>
        </Files>

        <!-- Enabled: true/false    | Enables/Disables the !stick- and !unstick-Command. -->
        <!-- LogEnabled: true/false | Enables/Disables the Logging of this feature. -->
        <Stick Enabled="true" LogEnabled="true">
            <!-- The Help-Message part, which will explain the !stick- and !unstick-Command -->
            <HelpMessage>
                [B]!stick {Nickname|Database ID} [Channel ID] [StickTime][/B]
                Sets the Sticky-State to given client in given channel. The StickTime (optional) specifies the duration in minutes that a client is detained therein.
                Example: [I]!stick 5[/I]

                [B]!unstick {Nickname|Database ID}[/B]
                Releases every Sticky-State from given client.
                Example: [I]!unstick 5[/I]
            </HelpMessage>
			
            <!-- Denied/Permitted-Tags can be placed here. For further details look at the example in the Vote feature.-->
            <Permitted>
                <Group>2</Group>
                <Group>6</Group>
            </Permitted>
        </Stick>
    </Control>

    <!-- Enabled: true/false | Enables/Disables the Random-Event-Messages feature. -->
    <!-- This feature randomly picks a user from the whole user list and raises an event, when this user is currently online. -->
    <Event Enabled="true">
        <Events>
            <!-- Enabled: true/false    | Enables/Disables this Event. -->
            <!-- LogEnabled: true/false | Enables/Disables the Logging of this feature. -->
            <EventDefinition Enabled="false" LogEnabled="true">
                <!-- The event name -->
                <Name>Random</Name>
				
                <!-- The list of behaviors, which will be raised, when the random event is fired. -->
                <EventBehaviors>
                    <EventBehavior>
                        <!-- Behavior: Poke/Message/Web | The behavior, which will be raised -->
                        <!-- Poke: Pokes the picked user. -->
                        <!-- Message: Sends a private message to the picked user. -->
                        <!-- Web: Silently calls a web page with some arguments. -->
                        <Behavior>Poke</Behavior>
						
                        <!-- The message, which will be used, when the event is fired. -->
                        <TextMessage>Hey [CLIENT_NICKNAME], you were just chosen by [EVENT_NAME].</TextMessage>
                    </EventBehavior>
                </EventBehaviors>
				
                <!-- Specifies the Interval in which this event fires. -->
                <Interval>30</Interval>
				
                <!-- Denied/Permitted-Tags can be placed here. For further details look at the example in the Vote feature.-->
                <Denied>
                    <Group>8</Group>
                </Denied>
            </EventDefinition>
        </Events>
    </Event>

    <!-- Enabled: true/false    | Enables/Disables the Idle-Channel. -->
    <!-- LogEnabled: true/false | Enables/Disables the Logging of this feature. -->
    <Idle Enabled="true">
        <!-- The ID of the Idle-Channel, where the user will be moved, when idling. -->
        <Channel>3</Channel>
		
        <!-- The time in seconds, after which the user becomes idling. -->
        <IdleTime>300</IdleTime>
		
        <!-- Denied/Permitted-Tags can be placed here. For further details look at the example in the Vote feature.-->
    </Idle>

    <!-- Enabled: true/false | Enables/Disables the Messages feature. -->
    <Message Enabled="true">
        <Messages>
            <!-- Enabled: true/false    | Enables/Disables this Message, which is a Advertising Message. -->
            <!-- LogEnabled: true/false | Enables/Disables the Logging of this Message. -->
            <MessageDefinition Enabled="true">
                <!-- MessageType: Advert/Global/Welcome | Specifies the type of this Message. -->
                <MessageType>Advert</MessageType>
				
                <!-- The message, which will be send. -->
                <TextMessage>This is an advertising message.</TextMessage>
                
                <!-- The interval in minutes in which this advert message will be repeated. -->
                <Interval>60</Interval>
            </MessageDefinition>

            <!-- Enabled: true/false    | Enables/Disables this Message, which is a Global Message. -->
            <!-- LogEnabled: true/false | Enables/Disables the Logging of this Message. -->
            <MessageDefinition Enabled="true">
                <!-- MessageType: Advert/Global/Welcome | Specifies the type of this Message. -->
                <MessageType>Global</MessageType>
				
                <!-- The message, which will be send. -->
                <TextMessage>This is a global advertising message.</TextMessage>
				
                <!-- The interval in minutes in which this global message will be repeated. -->
                <Interval>60</Interval>
            </MessageDefinition>

            <!-- Enabled: true/false    | Enables/Disables this Message, which is a Welcome Message. -->
            <!-- LogEnabled: true/false | Enables/Disables the Logging of this Message. -->
            <MessageDefinition Enabled="true">
                <!-- MessageType: Advert/Global/Welcome | Specifies the type of this Message. -->
                <MessageType>Welcome</MessageType>
				
                <!-- The message, which will be send. -->
                <TextMessage>Welcome [B][CLIENT_NICKNAME][/B]!</TextMessage>
				
                <!-- The ID of the home-channel. -->
                <Channel>1</Channel>
            </MessageDefinition>
        </Messages>
    </Message>

    <!-- Enabled: true/false    | Enables/Disables the Recording Behavior. -->
    <!-- LogEnabled: true/false | Enables/Disables the Logging of this feature. -->
    <Record Enabled="true">
        <!-- Behavior: Channel/Server/Sticky | The punishment behavior, which will be used, when someone tries to record. -->
        <!-- Channel: Kicks the user from current channel. -->
        <!-- Server: Kicks the user from the server. -->
        <!-- Sticky: Moves the user into the sticky channel. -->
        <Behavior>Channel</Behavior>
		
        <!-- The Message that will be shown, when someone get kicked by this feature. -->
        <KickMessage>Recording prohibited!</KickMessage>
		
        <!-- Denied/Permitted-Tags can be placed here. For further details look at the example in the Vote feature.-->
    </Record>

    <!-- Enabled: true/false    | Enables/Disables the Sticky-Channel. -->
    <!-- LogEnabled: true/false | Enables/Disables the Logging of this feature. -->
    <Sticky Enabled="true">
        <!-- The ID of the sticky-channel. -->
        <Channel>4</Channel>
		
        <!-- The time in minutes in which the user is locked into the sticky channel. -->
        <StickTime>30</StickTime>
		
        <!-- Denied/Permitted-Tags can be placed here. For further details look at the example in the Vote feature.-->
    </Sticky>

    <!-- Enabled: true/false    | Enables/Disables the Voting feature. -->
    <!-- LogEnabled: true/false | Enables/Disables the Logging of this feature. -->
    <Vote Enabled="true">
        <!-- The number of compliants needed to punish the voted user. -->
        <NeededCompliants>4</NeededCompliants>
		
        <!-- Behavior: Channel/Server/Sticky | The punishment behavior, which will be used. -->
        <!-- Channel: Kicks the user from current channel. -->
        <!-- Server: Kicks the user from the server. -->
        <!-- Sticky: Moves the user into the sticky channel. -->
        <Behavior>Sticky</Behavior>
		
        <!-- The Message that will be shown, when someone get punished by this feature. -->
        <KickMessage>There are complains against you!</KickMessage>
        
        <!-- Permitted-Tag: Use Group-Tags to specify IDs of groups, that are permitted to use or get handled by this feature. -->
        <!-- Denied-Tag: Use Group-Tags to specify IDs of groups, that are denied to use or get handled by this feature. -->
        <!-- NOTE: Only one Permitted OR Denied-Tag is necessary, cause they rule out each other. -->
        <Permitted>
            <!-- Group 3 (Server Normal), 4 (Server Guest), 7 (Channel Voice) and 8 (Channel Guest) can only be punished by vote. -->
            <Group>3</Group>
            <Group>4</Group>
            <Group>7</Group>
            <Group>8</Group>
        </Permitted>
        <Denied>
            <!-- Group 2 (Server Admin) and 5 (Channel Admin) can not be punished by vote, to prevent kicking admins. Only members can vote-kick other members -->
            <Group>2</Group>
            <Group>5</Group>
        </Denied>
    </Vote>

</InstanceSettings>